<?xml version="1.0" encoding="utf-8"?>
<!DOCTYPE install PUBLIC "-//Joomla! 2.5//DTD template 1.0//EN" "http://www.joomla.org/xml/dtd/1.6/template-install.dtd">
<extension version="3.1" type="template" client="site">
	<name>wwOosterhout</name>
	<creationDate>3-1-2015</creationDate>
	<author>Jelte de Jong</author>
	<authorEmail>jdjong@hjalte.nl</authorEmail>
	<authorUrl>www.hjalte.nl</authorUrl>
	<copyright></copyright>
	<license>GNU General Public License version 2 or later</license>
	<version>1.0</version>
	<description>Template in eerste instantie gemaakt voor de wereldwinkel in Oosterhout.</description>

	<files>
		<folder>css</folder>
		<folder>img</folder>
		<folder>js</folder>
		<filename>index.php</filename>
		<filename>templateDetails.xml</filename>
	</files>
	<positions>
		<position>debug</position>
		<position>position-0</position>
		<position>position-1</position>
		<position>position-2</position>
		<position>position-3</position>
		<position>position-4</position>
		<position>position-5</position>
		<position>position-6</position>
		<position>position-7</position>
		<position>position-8</position>
		<position>position-9</position>
		<position>position-10</position>
		<position>position-11</position>
		<position>position-12</position>
		<position>position-13</position>
		<position>position-14</position>
	</positions>
</extension>
